LICENSE
README.md
setup.py
autographObsidian/__init__.py
autographObsidian/autograph.py
autograph_obsidian.egg-info/PKG-INFO
autograph_obsidian.egg-info/SOURCES.txt
autograph_obsidian.egg-info/dependency_links.txt
autograph_obsidian.egg-info/entry_points.txt
autograph_obsidian.egg-info/requires.txt
autograph_obsidian.egg-info/top_level.txt