Metadata-Version: 2.1
Name: autograph-obsidian
Version: 0.3
Summary: Automatic knowledge graph generation.
Home-page: https://github.com/J-E-J-S/autograph-obsidian
Author: James Sanders
Author-email: james.sanders1711@gmail.com
License-File: LICENSE
